pytest_jsonschema/__init__.py
pytest_jsonschema/fixtures.py
pytest_jsonschema/loaders.py
pytest_jsonschema/types.py
pytest_jsonschema/validator.py
pytest_jsonschema/schemas/__init__.py
pytest_jsonschema/schemas/ansible-vars.json
pytest_jsonschema/schemas/ansible.json
pytest_jsonschema/schemas/docker-compose.json
pytest_jsonschema/schemas/github-action.json
pytest_jsonschema/schemas/github-funding.json
pytest_jsonschema/schemas/github-issue-config.json
pytest_jsonschema/schemas/github-issue-forms.json
pytest_jsonschema/schemas/github-workflow.json
pytest_jsonschema/schemas/gitlab-ci.json
pytest_jsonschema/schemas/package.json
pytest_jsonschema/schemas/pre-commit-config.json
pytest_jsonschema/schemas/pre-commit-hooks.json
pytest_jsonschema/schemas/prettierrc.json
pytest_jsonschema/schemas/pyproject.json
pytest_jsonschema/schemas/tsconfig.json
pytest_jsonschema/utils/__init__.py
pytest_jsonschema/utils/update_schema.py
pytest_jsonschema-1.0.0.dist-info/METADATA
pytest_jsonschema-1.0.0.dist-info/WHEEL
pytest_jsonschema-1.0.0.dist-info/entry_points.txt
pytest_jsonschema-1.0.0.dist-info/licenses/LICENSE
pytest_jsonschema-1.0.0.dist-info/RECORD
