Metadata-Version: 2.4
Name: pytest-jsonschema
Version: 1.0.0
Summary: A pytest plugin to perform JSONSchema validations
Project-URL: Homepage, https://github.com/collective/pytest-jsonschema
Project-URL: PyPI, https://pypi.org/project/pytest-jsonschema
Project-URL: Source, https://github.com/collective/pytest-jsonschema
Project-URL: Tracker, https://github.com/collective/pytest-jsonschema/issues
Author-email: Érico Andrei <ericof@plone.org>
Maintainer-email: Érico Andrei <ericof@plone.org>
License: 
License-File: LICENSE
Keywords: pytest,testing
Classifier: Development Status :: 5 - Production/Stable
Classifier: Framework :: Pytest
Classifier: Intended Audience :: Developers
Classifier: Operating System :: OS Independent
Classifier: Programming Language :: Python
Classifier: Programming Language :: Python :: 3 :: Only
Classifier: Programming Language :: Python :: 3.10
Classifier: Programming Language :: Python :: 3.11
Classifier: Programming Language :: Python :: 3.12
Classifier: Programming Language :: Python :: 3.13
Classifier: Programming Language :: Python :: Implementation :: CPython
Classifier: Topic :: Software Development :: Testing
Requires-Python: >=3.10
Requires-Dist: jsonschema
Requires-Dist: pytest>=6.2.0
Requires-Dist: ruamel-yaml
Requires-Dist: tomli==2.0.1; python_version <= '3.11'
